LICENSE
emoji/__init__.py
emoji/__main__.py
emoji/emoji.py
emoji/search.py
emoji/test.py
emoji_search-1.2.0.dist-info/entry_points.txt
emoji_search-1.2.0.dist-info/LICENSE
emoji_search-1.2.0.dist-info/WHEEL
emoji_search-1.2.0.dist-info/METADATA
emoji_search-1.2.0.dist-info/RECORD
