Metadata-Version: 2.1
Name: emoji-search
Version: 1.2.0
Summary: The #1 Python tool for miscellaneous emoji info
Home-page: https://github.com/dawsonbooth/emoji-search
License: MIT
Keywords: cli,console,emoji,unicode,emoticon,emojipedia,scrape,web,search
Author: Dawson Booth
Author-email: pypi@dawsonbooth.com
Requires-Python: >=3.6,<4.0
Classifier: Environment :: Console
Classifier: License :: OSI Approved :: MIT License
Classifier: Operating System :: OS Independent
Classifier: Programming Language :: Python :: 3
Classifier: Programming Language :: Python :: 3.6
Classifier: Programming Language :: Python :: 3.7
Classifier: Programming Language :: Python :: 3.8
Classifier: Programming Language :: Python :: 3.9
Requires-Dist: beautifulsoup4 (>=4.9.1,<5.0.0)
Requires-Dist: lxml (>=4.5.1,<5.0.0)
Requires-Dist: requests (>=2.24.0,<3.0.0)
Project-URL: Repository, https://github.com/dawsonbooth/emoji-search
